[
  {
    "款": 9,
    "款名": "消防費",
    "項": 1,
    "項名": "消防費",
    "目": 0,
    "目名": "",
    "レベル": "節",
    "番号": "2",
    "名称": "給料                1.261,",
    "金額_千円": 275
  },
  {
    "款": 9,
    "款名": "消防費",
    "項": 1,
    "項名": "消防費",
    "目": 0,
    "目名": "",
    "レベル": "節",
    "番号": "3",
    "名称": "職員手当等        911.",
    "金額_千円": 950
  },
  {
    "款": 9,
    "款名": "消防費",
    "項": 1,
    "項名": "消防費",
    "目": 0,
    "目名": "",
    "レベル": "節",
    "番号": "4",
    "名称": "共済費                439,",
    "金額_千円": 918
  },
  {
    "款": 9,
    "款名": "消防費",
    "項": 1,
    "項名": "消防費",
    "目": 0,
    "目名": "",
    "レベル": "節",
    "番号": "7",
    "名称": "報償費",
    "金額_千円": 791
  },
  {
    "款": 9,
    "款名": "消防費",
    "項": 1,
    "項名": "消防費",
    "目": 0,
    "目名": "",
    "レベル": "節",
    "番号": "8",
    "名称": "旅費",
    "金額_千円": 4543
  },
  {
    "款": 9,
    "款名": "消防費",
    "項": 1,
    "項名": "消防費",
    "目": 0,
    "目名": "",
    "レベル": "節",
    "番号": "10",
    "名称": "需用費                107,",
    "金額_千円": 279
  },
  {
    "款": 9,
    "款名": "消防費",
    "項": 1,
    "項名": "消防費",
    "目": 0,
    "目名": "",
    "レベル": "説明",
    "番号": "005",
    "名称": "消防水利管理事業費",
    "金額_千円": 36405
  },
  {
    "款": 9,
    "款名": "消防費",
    "項": 1,
    "項名": "消防費",
    "目": 0,
    "目名": "",
    "レベル": "説明",
    "番号": "006",
    "名称": "消防庁舎管理事業費",
    "金額_千円": 80572
  },
  {
    "款": 9,
    "款名": "消防費",
    "項": 1,
    "項名": "消防費",
    "目": 0,
    "目名": "",
    "レベル": "説明",
    "番号": "003",
    "名称": "消防活動費",
    "金額_千円": 23804
  },
  {
    "款": 9,
    "款名": "消防費",
    "項": 1,
    "項名": "消防費",
    "目": 0,
    "目名": "",
    "レベル": "説明",
    "番号": "001",
    "名称": "消防活動費",
    "金額_千円": 23804
  },
  {
    "款": 9,
    "款名": "消防費",
    "項": 1,
    "項名": "消防費",
    "目": 0,
    "目名": "",
    "レベル": "節",
    "番号": "12",
    "名称": "委託料          121,",
    "金額_千円": 882
  },
  {
    "款": 9,
    "款名": "消防費",
    "項": 1,
    "項名": "消防費",
    "目": 0,
    "目名": "",
    "レベル": "説明",
    "番号": "004",
    "名称": "表急活動費                                            16,",
    "金額_千円": 807
  },
  {
    "款": 9,
    "款名": "消防費",
    "項": 1,
    "項名": "消防費",
    "目": 0,
    "目名": "",
    "レベル": "説明",
    "番号": "001",
    "名称": "救急活動費",
    "金額_千円": 16807
  },
  {
    "款": 9,
    "款名": "消防費",
    "項": 1,
    "項名": "消防費",
    "目": 0,
    "目名": "",
    "レベル": "節",
    "番号": "18",
    "名称": "負担金、補助",
    "金額_千円": 34
  },
  {
    "款": 9,
    "款名": "消防費",
    "項": 1,
    "項名": "消防費",
    "目": 0,
    "目名": "",
    "レベル": "説明",
    "番号": "513",
    "名称": "富士地域MC協議会負担金",
    "金額_千円": 55
  },
  {
    "款": 9,
    "款名": "消防費",
    "項": 1,
    "項名": "消防費",
    "目": 0,
    "目名": "",
    "レベル": "説明",
    "番号": "005",
    "名称": "予防広報活動旨",
    "金額_千円": 8345
  },
  {
    "款": 9,
    "款名": "消防費",
    "項": 1,
    "項名": "消防費",
    "目": 0,
    "目名": "",
    "レベル": "説明",
    "番号": "001",
    "名称": "予防広報事業費                        6,",
    "金額_千円": 489
  },
  {
    "款": 9,
    "款名": "消防費",
    "項": 1,
    "項名": "消防費",
    "目": 0,
    "目名": "",
    "レベル": "説明",
    "番号": "953",
    "名称": "167, 333     4.620     1.608     13, 200    22.900    134,",
    "金額_千円": 245
  },
  {
    "款": 9,
    "款名": "消防費",
    "項": 1,
    "項名": "消防費",
    "目": 0,
    "目名": "",
    "レベル": "節",
    "番号": "26",
    "名称": "公課費",
    "金額_千円": 2022
  },
  {
    "款": 9,
    "款名": "消防費",
    "項": 1,
    "項名": "消防費",
    "目": 0,
    "目名": "",
    "レベル": "節",
    "番号": "1",
    "名称": "報酬          66.",
    "金額_千円": 190
  },
  {
    "款": 9,
    "款名": "消防費",
    "項": 1,
    "項名": "消防費",
    "目": 0,
    "目名": "",
    "レベル": "節",
    "番号": "7",
    "名称": "報償費",
    "金額_千円": 20300
  },
  {
    "款": 9,
    "款名": "消防費",
    "項": 1,
    "項名": "消防費",
    "目": 0,
    "目名": "",
    "レベル": "節",
    "番号": "8",
    "名称": "旅費",
    "金額_千円": 36
  },
  {
    "款": 9,
    "款名": "消防費",
    "項": 1,
    "項名": "消防費",
    "目": 0,
    "目名": "",
    "レベル": "説明",
    "番号": "002",
    "名称": "消防音楽隊等運営事業費",
    "金額_千円": 856
  },
  {
    "款": 9,
    "款名": "消防費",
    "項": 1,
    "項名": "消防費",
    "目": 0,
    "目名": "",
    "レベル": "説明",
    "番号": "006",
    "名称": "富士市・富士宮市消防指令センター偶                   147,",
    "金額_千円": 807
  },
  {
    "款": 9,
    "款名": "消防費",
    "項": 1,
    "項名": "消防費",
    "目": 0,
    "目名": "",
    "レベル": "説明",
    "番号": "001",
    "名称": "富士市・富士宮市消防指令センター運営事業費",
    "金額_千円": 147807
  },
  {
    "款": 9,
    "款名": "消防費",
    "項": 1,
    "項名": "消防費",
    "目": 0,
    "目名": "",
    "レベル": "説明",
    "番号": "007",
    "名称": "遭難対策費",
    "金額_千円": 527
  },
  {
    "款": 9,
    "款名": "消防費",
    "項": 1,
    "項名": "消防費",
    "目": 0,
    "目名": "",
    "レベル": "説明",
    "番号": "001",
    "名称": "遭難対策事業江",
    "金額_千円": 97
  },
  {
    "款": 9,
    "款名": "消防費",
    "項": 1,
    "項名": "消防費",
    "目": 0,
    "目名": "",
    "レベル": "説明",
    "番号": "002",
    "名称": "道難対策助成費",
    "金額_千円": 430
  },
  {
    "款": 9,
    "款名": "消防費",
    "項": 1,
    "項名": "消防費",
    "目": 0,
    "目名": "",
    "レベル": "説明",
    "番号": "001",
    "名称": "給与費                                           66,",
    "金額_千円": 490
  },
  {
    "款": 9,
    "款名": "消防費",
    "項": 1,
    "項名": "消防費",
    "目": 0,
    "目名": "",
    "レベル": "説明",
    "番号": "001",
    "名称": "消防団員 800人",
    "金額_千円": 66490
  },
  {
    "款": 9,
    "款名": "消防費",
    "項": 1,
    "項名": "消防費",
    "目": 0,
    "目名": "",
    "レベル": "説明",
    "番号": "002",
    "名称": "消防団管理費                                      84,",
    "金額_千円": 160
  },
  {
    "款": 9,
    "款名": "消防費",
    "項": 1,
    "項名": "消防費",
    "目": 0,
    "目名": "",
    "レベル": "説明",
    "番号": "001",
    "名称": "消防団運営管理費                          55,",
    "金額_千円": 253
  },
  {
    "款": 9,
    "款名": "消防費",
    "項": 1,
    "項名": "消防費",
    "目": 0,
    "目名": "",
    "レベル": "説明",
    "番号": "003",
    "名称": "消防団詰所管理事業費                         21,",
    "金額_千円": 642
  },
  {
    "款": 9,
    "款名": "消防費",
    "項": 1,
    "項名": "消防費",
    "目": 0,
    "目名": "",
    "レベル": "説明",
    "番号": "003",
    "名称": "消防団活動費",
    "金額_千円": 21303
  },
  {
    "款": 9,
    "款名": "消防費",
    "項": 1,
    "項名": "消防費",
    "目": 0,
    "目名": "",
    "レベル": "説明",
    "番号": "001",
    "名称": "消防団活動費                            2.",
    "金額_千円": 53
  },
  {
    "款": 9,
    "款名": "消防費",
    "項": 1,
    "項名": "消防費",
    "目": 0,
    "目名": "",
    "レベル": "説明",
    "番号": "003",
    "名称": "消防団交付金",
    "金額_千円": 16500
  },
  {
    "款": 9,
    "款名": "消防費",
    "項": 1,
    "項名": "消防費",
    "目": 0,
    "目名": "",
    "レベル": "説明",
    "番号": "760",
    "名称": "410.009    86, 751     43,907    314.300            138,",
    "金額_千円": 553
  },
  {
    "款": 9,
    "款名": "消防費",
    "項": 1,
    "項名": "消防費",
    "目": 0,
    "目名": "",
    "レベル": "節",
    "番号": "8",
    "名称": "旅費",
    "金額_千円": 648
  },
  {
    "款": 9,
    "款名": "消防費",
    "項": 1,
    "項名": "消防費",
    "目": 0,
    "目名": "",
    "レベル": "説明",
    "番号": "001",
    "名称": "消防施設整備費                              427,",
    "金額_千円": 756
  },
  {
    "款": 9,
    "款名": "消防費",
    "項": 1,
    "項名": "消防費",
    "目": 0,
    "目名": "",
    "レベル": "説明",
    "番号": "001",
    "名称": "当火栓整備事業費",
    "金額_千円": 66834
  },
  {
    "款": 9,
    "款名": "消防費",
    "項": 1,
    "項名": "消防費",
    "目": 0,
    "目名": "",
    "レベル": "節",
    "番号": "10",
    "名称": "需用費",
    "金額_千円": 570
  },
  {
    "款": 9,
    "款名": "消防費",
    "項": 1,
    "項名": "消防費",
    "目": 0,
    "目名": "",
    "レベル": "説明",
    "番号": "004",
    "名称": "耐震性貯水槽整備事業費                     13,",
    "金額_千円": 58
  },
  {
    "款": 9,
    "款名": "消防費",
    "項": 1,
    "項名": "消防費",
    "目": 0,
    "目名": "",
    "レベル": "節",
    "番号": "18",
    "名称": "負担金、補助",
    "金額_千円": 66834
  },
  {
    "款": 9,
    "款名": "消防費",
    "項": 1,
    "項名": "消防費",
    "目": 0,
    "目名": "",
    "レベル": "説明",
    "番号": "002",
    "名称": "消防団施設整備費",
    "金額_千円": 69004
  },
  {
    "款": 9,
    "款名": "消防費",
    "項": 1,
    "項名": "消防費",
    "目": 0,
    "目名": "",
    "レベル": "説明",
    "番号": "002",
    "名称": "消防団車両整備事業費                         64.",
    "金額_千円": 60
  },
  {
    "款": 9,
    "款名": "消防費",
    "項": 1,
    "項名": "消防費",
    "目": 0,
    "目名": "",
    "レベル": "説明",
    "番号": "001",
    "名称": "給与費",
    "金額_千円": 497
  },
  {
    "款": 9,
    "款名": "消防費",
    "項": 1,
    "項名": "消防費",
    "目": 0,
    "目名": "",
    "レベル": "節",
    "番号": "5",
    "名称": "災害補償費",
    "金額_千円": 200
  },
  {
    "款": 9,
    "款名": "消防費",
    "項": 1,
    "項名": "消防費",
    "目": 0,
    "目名": "",
    "レベル": "説明",
    "番号": "002",
    "名称": "水防協議会委員 4人",
    "金額_千円": 40
  },
  {
    "款": 9,
    "款名": "消防費",
    "項": 1,
    "項名": "消防費",
    "目": 0,
    "目名": "",
    "レベル": "節",
    "番号": "7",
    "名称": "報償費",
    "金額_千円": 11
  },
  {
    "款": 9,
    "款名": "消防費",
    "項": 1,
    "項名": "消防費",
    "目": 0,
    "目名": "",
    "レベル": "説明",
    "番号": "002",
    "名称": "水防対策費                                 13,",
    "金額_千円": 951
  },
  {
    "款": 9,
    "款名": "消防費",
    "項": 1,
    "項名": "消防費",
    "目": 0,
    "目名": "",
    "レベル": "説明",
    "番号": "001",
    "名称": "一般事務費",
    "金額_千円": 18
  },
  {
    "款": 9,
    "款名": "消防費",
    "項": 1,
    "項名": "消防費",
    "目": 0,
    "目名": "",
    "レベル": "節",
    "番号": "8",
    "名称": "旅費",
    "金額_千円": 8
  },
  {
    "款": 9,
    "款名": "消防費",
    "項": 1,
    "項名": "消防費",
    "目": 0,
    "目名": "",
    "レベル": "節",
    "番号": "11",
    "名称": "役務費",
    "金額_千円": 215
  },
  {
    "款": 9,
    "款名": "消防費",
    "項": 1,
    "項名": "消防費",
    "目": 0,
    "目名": "",
    "レベル": "節",
    "番号": "12",
    "名称": "委託料           3,",
    "金額_千円": 74
  },
  {
    "款": 9,
    "款名": "消防費",
    "項": 1,
    "項名": "消防費",
    "目": 0,
    "目名": "",
    "レベル": "節",
    "番号": "13",
    "名称": "使用料及び賃",
    "金額_千円": 947
  },
  {
    "款": 9,
    "款名": "消防費",
    "項": 1,
    "項名": "消防費",
    "目": 0,
    "目名": "",
    "レベル": "節",
    "番号": "15",
    "名称": "原材料費",
    "金額_千円": 72
  },
  {
    "款": 9,
    "款名": "消防費",
    "項": 1,
    "項名": "消防費",
    "目": 0,
    "目名": "",
    "レベル": "説明",
    "番号": "565",
    "名称": "165, 514    42, 051     65, 912    37,400     5.135",
    "金額_千円": 99118
  },
  {
    "款": 9,
    "款名": "消防費",
    "項": 1,
    "項名": "消防費",
    "目": 0,
    "目名": "",
    "レベル": "節",
    "番号": "1",
    "名称": "報酬          3.",
    "金額_千円": 61
  },
  {
    "款": 9,
    "款名": "消防費",
    "項": 1,
    "項名": "消防費",
    "目": 0,
    "目名": "",
    "レベル": "節",
    "番号": "3",
    "名称": "職員手当等        11,",
    "金額_千円": 399
  },
  {
    "款": 9,
    "款名": "消防費",
    "項": 1,
    "項名": "消防費",
    "目": 0,
    "目名": "",
    "レベル": "節",
    "番号": "4",
    "名称": "共済費",
    "金額_千円": 531
  },
  {
    "款": 9,
    "款名": "消防費",
    "項": 1,
    "項名": "消防費",
    "目": 0,
    "目名": "",
    "レベル": "節",
    "番号": "7",
    "名称": "報償費",
    "金額_千円": 561
  },
  {
    "款": 9,
    "款名": "消防費",
    "項": 1,
    "項名": "消防費",
    "目": 0,
    "目名": "",
    "レベル": "節",
    "番号": "8",
    "名称": "旅費",
    "金額_千円": 526
  },
  {
    "款": 9,
    "款名": "消防費",
    "項": 1,
    "項名": "消防費",
    "目": 0,
    "目名": "",
    "レベル": "節",
    "番号": "10",
    "名称": "需用費            47,",
    "金額_千円": 114
  },
  {
    "款": 9,
    "款名": "消防費",
    "項": 1,
    "項名": "消防費",
    "目": 0,
    "目名": "",
    "レベル": "説明",
    "番号": "003",
    "名称": "備間資機材整備事業費                          26,",
    "金額_千円": 942
  },
  {
    "款": 9,
    "款名": "消防費",
    "項": 1,
    "項名": "消防費",
    "目": 0,
    "目名": "",
    "レベル": "節",
    "番号": "12",
    "名称": "委託料",
    "金額_千円": 24890
  },
  {
    "款": 9,
    "款名": "消防費",
    "項": 1,
    "項名": "消防費",
    "目": 0,
    "目名": "",
    "レベル": "節",
    "番号": "14",
    "名称": "工事請負費        5,",
    "金額_千円": 131
  },
  {
    "款": 9,
    "款名": "消防費",
    "項": 1,
    "項名": "消防費",
    "目": 0,
    "目名": "",
    "レベル": "節",
    "番号": "18",
    "名称": "負担金、補助",
    "金額_千円": 40962
  },
  {
    "款": 9,
    "款名": "消防費",
    "項": 1,
    "項名": "消防費",
    "目": 0,
    "目名": "",
    "レベル": "説明",
    "番号": "006",
    "名称": "国民保護事業費",
    "金額_千円": 990
  },
  {
    "款": 9,
    "款名": "消防費",
    "項": 1,
    "項名": "消防費",
    "目": 0,
    "目名": "",
    "レベル": "説明",
    "番号": "003",
    "名称": "防災無線費                                        63,",
    "金額_千円": 236
  },
  {
    "款": 9,
    "款名": "消防費",
    "項": 1,
    "項名": "消防費",
    "目": 0,
    "目名": "",
    "レベル": "説明",
    "番号": "001",
    "名称": "防災無線整備費                                35,",
    "金額_千円": 858
  },
  {
    "款": 9,
    "款名": "消防費",
    "項": 1,
    "項名": "消防費",
    "目": 0,
    "目名": "",
    "レベル": "説明",
    "番号": "002",
    "名称": "防災無線管理費",
    "金額_千円": 27378
  },
  {
    "款": 9,
    "款名": "消防費",
    "項": 1,
    "項名": "教育総務費",
    "目": 0,
    "目名": "",
    "レベル": "説明",
    "番号": "897",
    "名称": "5, 486      411     1.926                    3,",
    "金額_千円": 971
  },
  {
    "款": 9,
    "款名": "消防費",
    "項": 1,
    "項名": "教育総務費",
    "目": 0,
    "目名": "",
    "レベル": "説明",
    "番号": "949",
    "名称": "888,546    35, 403     2, 371            11.049",
    "金額_千円": 910529
  },
  {
    "款": 9,
    "款名": "消防費",
    "項": 1,
    "項名": "教育総務費",
    "目": 0,
    "目名": "",
    "レベル": "説明",
    "番号": "001",
    "名称": "給与費                              3.",
    "金額_千円": 672
  },
  {
    "款": 9,
    "款名": "消防費",
    "項": 1,
    "項名": "教育総務費",
    "目": 0,
    "目名": "",
    "レベル": "説明",
    "番号": "001",
    "名称": "教育委員 人                              3",
    "金額_千円": 430
  },
  {
    "款": 9,
    "款名": "消防費",
    "項": 1,
    "項名": "教育総務費",
    "目": 0,
    "目名": "",
    "レベル": "節",
    "番号": "7",
    "名称": "報償費",
    "金額_千円": 106
  },
  {
    "款": 9,
    "款名": "消防費",
    "項": 1,
    "項名": "教育総務費",
    "目": 0,
    "目名": "",
    "レベル": "節",
    "番号": "8",
    "名称": "旅費             230",
    "金額_千円": 62
  },
  {
    "款": 9,
    "款名": "消防費",
    "項": 1,
    "項名": "教育総務費",
    "目": 0,
    "目名": "",
    "レベル": "説明",
    "番号": "003",
    "名称": "中学校部活動地域移行協議会要員 6人",
    "金額_千円": 180
  },
  {
    "款": 9,
    "款名": "消防費",
    "項": 1,
    "項名": "教育総務費",
    "目": 0,
    "目名": "",
    "レベル": "節",
    "番号": "10",
    "名称": "需用費",
    "金額_千円": 83
  },
  {
    "款": 9,
    "款名": "消防費",
    "項": 1,
    "項名": "教育総務費",
    "目": 0,
    "目名": "",
    "レベル": "節",
    "番号": "18",
    "名称": "負担金、補助",
    "金額_千円": 99
  },
  {
    "款": 9,
    "款名": "消防費",
    "項": 1,
    "項名": "教育総務費",
    "目": 0,
    "目名": "",
    "レベル": "節",
    "番号": "1",
    "名称": "報酬",
    "金額_千円": 33721
  },
  {
    "款": 9,
    "款名": "消防費",
    "項": 1,
    "項名": "教育総務費",
    "目": 0,
    "目名": "",
    "レベル": "説明",
    "番号": "001",
    "名称": "給与費                             625,",
    "金額_千円": 960
  },
  {
    "款": 9,
    "款名": "消防費",
    "項": 1,
    "項名": "教育総務費",
    "目": 0,
    "目名": "",
    "レベル": "説明",
    "番号": "001",
    "名称": "特別職 1人                              15,",
    "金額_千円": 263
  },
  {
    "款": 9,
    "款名": "消防費",
    "項": 1,
    "項名": "教育総務費",
    "目": 0,
    "目名": "",
    "レベル": "節",
    "番号": "2",
    "名称": "給料          246,",
    "金額_千円": 525
  },
  {
    "款": 9,
    "款名": "消防費",
    "項": 1,
    "項名": "教育総務費",
    "目": 0,
    "目名": "",
    "レベル": "説明",
    "番号": "003",
    "名称": "パートタイム会計年度任用職員  (雪育総務)",
    "金額_千円": 69084
  },
  {
    "款": 9,
    "款名": "消防費",
    "項": 1,
    "項名": "教育総務費",
    "目": 0,
    "目名": "",
    "レベル": "説明",
    "番号": "002",
    "名称": "管理事務局費                                       14.",
    "金額_千円": 2
  }
]